juliaPIV/__init__.py
juliaPIV/juliaPIV.py
juliaPIV/julia_compiler.py
juliaPIV/utils.py
juliaPIV/PIVPipelineUtility/Manifest.toml
juliaPIV/PIVPipelineUtility/Project.toml
juliaPIV/PIVPipelineUtility/package_compile_notes.txt
juliaPIV/PIVPipelineUtility/src/PIVPipelineUtility.jl
juliaPIV/PIVPipelineUtility/src/main.jl
juliaPIV/PIVPipelineUtility/src/precompile/precompile.jl
juliaPIV/PIVPipelineUtility/src/precompile/precompile.yaml
juliaPIV/PIVPipelineUtility/src/precompile/in/batch/precompile.txt
juliaPIV/PIVPipelineUtility/src/precompile/in/data/023999_1738857892141378616_252_1190.jpg
juliaPIV/PIVPipelineUtility/src/precompile/in/data/024000_1738857892153880912_252_1190.jpg
juliaPIV/PIVPipelineUtility/src/precompile/out/024000_1738857892153880912_252_1190.mat
juliaPIV/batcher/__init__.py
juliaPIV/batcher/batcher.py
juliaPIV/pivpipe/__init__.py
juliaPIV/pivpipe/pivpipe.py
juliapiv-1.0.11.dist-info/licenses/LICENSE
juliapiv-1.0.11.dist-info/METADATA
juliapiv-1.0.11.dist-info/WHEEL
juliapiv-1.0.11.dist-info/entry_points.txt
juliapiv-1.0.11.dist-info/top_level.txt
juliapiv-1.0.11.dist-info/RECORD
