Metadata-Version: 2.4
Name: juliaPIV
Version: 1.0.11
Summary: A pipeline for running JuliaPIV based on the workflow developed at OSU CEOAS
Author-email: Robin Shindelman <roshindelman@gmail.com>
License-Expression: MIT
Project-URL: Homepage, https://github.com/shindelr/juliaPIV
Project-URL: Issues, https://github.com/shindelr/juliaPIV/issues
Classifier: Programming Language :: Python :: 3
Classifier: Operating System :: OS Independent
Requires-Python: >=3.11
License-File: LICENSE
Requires-Dist: click>=8.0.0
Requires-Dist: PyYAML>=6.0.2
Requires-Dist: tqdm>=4.60.0
Requires-Dist: juliacall>=0.9.25
Requires-Dist: natsort>=8.4.0
Dynamic: license-file
